aioletterxpress/__init__.py
aioletterxpress/client.py
aioletterxpress/enums.py
aioletterxpress-0.1.0.dist-info/LICENSE
aioletterxpress-0.1.0.dist-info/WHEEL
aioletterxpress-0.1.0.dist-info/METADATA
aioletterxpress-0.1.0.dist-info/RECORD
