Metadata-Version: 2.1
Name: aioletterxpress
Version: 0.1.0
Summary: 
Author: Sebatian Lübke
Author-email: sebastian@luebke.io
Requires-Python: >=3.8,<4.0
Classifier: Programming Language :: Python :: 3
Classifier: Programming Language :: Python :: 3.8
Classifier: Programming Language :: Python :: 3.9
Requires-Dist: aiofiles (>=0.6.0,<0.7.0)
Requires-Dist: httpx (>=0.16.1,<0.17.0)
